jupyterlab_nbqueue/__init__.py
jupyterlab_nbqueue/_version.py
jupyterlab_nbqueue/accessible_directories_handler.py
jupyterlab_nbqueue/cmd_launcher.py
jupyterlab_nbqueue/conda_handler.py
jupyterlab_nbqueue/config.py
jupyterlab_nbqueue/handlers.py
jupyterlab_nbqueue/job_handler.py
jupyterlab_nbqueue/jobs_handler.py
jupyterlab_nbqueue/kernels_handler.py
jupyterlab_nbqueue/models.py
jupyterlab_nbqueue/common/__init__.py
jupyterlab_nbqueue/common/requests_utils.py
jupyterlab_nbqueue/common/variables.py
jupyterlab_nbqueue/labextension/build_log.json
jupyterlab_nbqueue/labextension/package.json
jupyterlab_nbqueue/labextension/schemas/jupyterlab-nbqueue/package.json.orig
jupyterlab_nbqueue/labextension/schemas/jupyterlab-nbqueue/plugin.json
jupyterlab_nbqueue/labextension/static/lib_index_js.3bdbd360604edab6e9ee.js
jupyterlab_nbqueue/labextension/static/lib_index_js.3bdbd360604edab6e9ee.js.map
jupyterlab_nbqueue/labextension/static/node_modules_babel_runtime_helpers_esm_extends_js-node_modules_emotion_memoize_dist_emotion-m-3c7f7e0.dd4db36ddc6543b50ed1.js
jupyterlab_nbqueue/labextension/static/node_modules_babel_runtime_helpers_esm_extends_js-node_modules_emotion_memoize_dist_emotion-m-3c7f7e0.dd4db36ddc6543b50ed1.js.map
jupyterlab_nbqueue/labextension/static/node_modules_babel_runtime_helpers_esm_extends_js-node_modules_emotion_memoize_dist_emotion-m-3c7f7e1.62d7ac9c3c49f319de62.js
jupyterlab_nbqueue/labextension/static/node_modules_babel_runtime_helpers_esm_extends_js-node_modules_emotion_memoize_dist_emotion-m-3c7f7e1.62d7ac9c3c49f319de62.js.map
jupyterlab_nbqueue/labextension/static/remoteEntry.d03d544f15febba67187.js
jupyterlab_nbqueue/labextension/static/remoteEntry.d03d544f15febba67187.js.map
jupyterlab_nbqueue/labextension/static/style.js
jupyterlab_nbqueue/labextension/static/style_index_js.04f699a1b7d121ce0bc5.js
jupyterlab_nbqueue/labextension/static/style_index_js.04f699a1b7d121ce0bc5.js.map
jupyterlab_nbqueue-0.1.47.dist-info/METADATA
jupyterlab_nbqueue-0.1.47.dist-info/WHEEL
jupyterlab_nbqueue-0.1.47.dist-info/licenses/LICENSE
jupyterlab_nbqueue-0.1.47.dist-info/RECORD
