Metadata-Version: 2.4
Name: jupyterlab_nbqueue
Version: 0.1.47
Summary: A JupyterLab extension for queuing notebooks executions.
Project-URL: Homepage, https://github.com/Navteca/jupyterlab-nbqueue.git
Project-URL: Bug Tracker, https://github.com/Navteca/jupyterlab-nbqueue.git/issues
Project-URL: Repository, https://github.com/Navteca/jupyterlab-nbqueue.git.git
Author-email: Navteca LLC <info@navteca.com>
License: BSD 3-Clause License
License-File: LICENSE
Keywords: jupyter,jupyterlab,jupyterlab-extension
Classifier: Framework :: Jupyter
Classifier: Framework :: Jupyter :: JupyterLab
Classifier: Framework :: Jupyter :: JupyterLab :: 4
Classifier: Framework :: Jupyter :: JupyterLab :: Extensions
Classifier: Framework :: Jupyter :: JupyterLab :: Extensions :: Prebuilt
Classifier: License :: OSI Approved :: BSD License
Classifier: Programming Language :: Python
Classifier: Programming Language :: Python :: 3
Classifier: Programming Language :: Python :: 3.8
Classifier: Programming Language :: Python :: 3.9
Classifier: Programming Language :: Python :: 3.10
Classifier: Programming Language :: Python :: 3.11
Classifier: Programming Language :: Python :: 3.12
Requires-Python: >=3.8
Requires-Dist: boto3<2,>=1.34.156
Requires-Dist: grpcio
Requires-Dist: grpcio-tools
Requires-Dist: jupyter-server<3,>=2.0.1
Requires-Dist: loguru
Requires-Dist: pydantic
Requires-Dist: pydantic-settings
Requires-Dist: python-dotenv
Requires-Dist: sqlalchemy
Provides-Extra: test
Requires-Dist: coverage; extra == 'test'
Requires-Dist: pytest; extra == 'test'
Requires-Dist: pytest-asyncio; extra == 'test'
Requires-Dist: pytest-cov; extra == 'test'
Requires-Dist: pytest-jupyter[server]>=0.6.0; extra == 'test'
